edgy/__init__.py
edgy/project/__init__.py
edgy/project/__main__.py
edgy/project/_require.py
edgy/project/_version.py
edgy/project/config.py
edgy/project/events.py
edgy/project/file.py
edgy/project/settings.py
edgy/project/testing.py
edgy/project/util.py
edgy/project/feature/__init__.py
edgy/project/feature/docker.py
edgy/project/feature/git.py
edgy/project/feature/make.py
edgy/project/feature/pylint.py
edgy/project/feature/pytest.py
edgy/project/feature/python.py
edgy/project/feature/sphinx.py
edgy/project/feature/webpack.py
edgy/project/feature/yapf.py
edgy/project/feature/template/Projectfile.j2
edgy/project/feature/template/console_script/__main__.py.j2
edgy/project/feature/template/pytest/coveragerc.j2
edgy/project/feature/template/pytest/travis.yml.j2
edgy/project/feature/template/python/package_init.py.j2
edgy/project/feature/template/python/setup.py.j2
edgy/project/feature/template/yapf/style.yapf.j2
edgy.project-0.3.2.dist-info/DESCRIPTION.rst
edgy.project-0.3.2.dist-info/METADATA
edgy.project-0.3.2.dist-info/RECORD
edgy.project-0.3.2.dist-info/WHEEL
edgy.project-0.3.2.dist-info/entry_points.txt
edgy.project-0.3.2.dist-info/metadata.json
edgy.project-0.3.2.dist-info/top_level.txt
