Metadata-Version: 2.0
Name: edgy.project
Version: 0.3.2
Summary: Strongly opinionated python project management.
Home-page: https://github.com/python-edgy/project
Author: Romain Dorgueil
Author-email: edgy@rdc.li
License: Apache License, Version 2.0
Download-URL: https://github.com/python-edgy/project/tarball/0.3.2
Platform: UNKNOWN
Requires-Dist: blessings (>=1.6,<1.7)
Requires-Dist: edgy.event (>=0.1,<0.2)
Requires-Dist: jinja2 (<3.0,>=2.8)
Requires-Dist: pip-tools (<2.0,>=1.9)
Requires-Dist: six (<2,>=1)
Requires-Dist: stevedore (<2,>=1)
Requires-Dist: tornado (>=4,<5)
Requires-Dist: yapf (>=0.16)
Provides-Extra: dev
Requires-Dist: coverage (<5.0,>=4.4); extra == 'dev'
Requires-Dist: pytest (>=3.1,<4.0); extra == 'dev'
Requires-Dist: pytest-cov (<3.0,>=2.5); extra == 'dev'
Requires-Dist: sphinx (<2.0,>=1.6); extra == 'dev'
Requires-Dist: sphinx-rtd-theme (<1.0,>=0.2); extra == 'dev'
